[
  {
    "inputs": [
      {
        "internalType": "contract ISuperfluid",
        "name": "host",
        "type": "address"
      },
      {
        "internalType": "contract IConstantFlowAgreementV1",
        "name": "cfa",
        "type": "address"
      },
      {
        "internalType": "contract ISuperToken",
        "name": "acceptedToken",
        "type": "address"
      },
      {
        "internalType": "address",
        "name": "dai",
        "type": "address"
      }
    ],
    "stateMutability": "nonpayable",
    "type": "constructor"
  },
  {
    "anonymous": false,
    "inputs": [
      {
        "indexed": true,
        "internalType": "address",
        "name": "charityAddress_",
        "type": "address"
      },
      {
        "indexed": true,
        "internalType": "bytes8",
        "name": "name_",
        "type": "bytes8"
      }
    ],
    "name": "CharityThisMonth",
    "type": "event"
  },
  {
    "anonymous": false,
    "inputs": [
      {
        "indexed": true,
        "internalType": "address",
        "name": "previousOwner",
        "type": "address"
      },
      {
        "indexed": true,
        "internalType": "address",
        "name": "newOwner",
        "type": "address"
      }
    ],
    "name": "OwnershipTransferred",
    "type": "event"
  },
  {
    "inputs": [],
    "name": "acountForDRfnds",
    "outputs": [],
    "stateMutability": "nonpayable",
    "type": "function"
  },
  {
    "inputs": [
      {
        "internalType": "bytes8",
        "name": "_charityName",
        "type": "bytes8"
      },
      {
        "internalType": "address",
        "name": "_charityAddress",
        "type": "address"
      },
      {
        "internalType": "bytes32",
        "name": "_link",
        "type": "bytes32"
      }
    ],
    "name": "addCharity",
    "outputs": [],
    "stateMutability": "nonpayable",
    "type": "function"
  },
  {
    "inputs": [
      {
        "internalType": "address",
        "name": "_conAddress",
        "type": "address"
      }
    ],
    "name": "addContract",
    "outputs": [],
    "stateMutability": "nonpayable",
    "type": "function"
  },
  {
    "inputs": [
      {
        "internalType": "contract IRedirect",
        "name": "addr",
        "type": "address"
      }
    ],
    "name": "addFlowDistributor",
    "outputs": [],
    "stateMutability": "nonpayable",
    "type": "function"
  },
  {
    "inputs": [
      {
        "internalType": "contract IGovernanceToken",
        "name": "_gtAdress",
        "type": "address"
      }
    ],
    "name": "addGovernanceToken",
    "outputs": [],
    "stateMutability": "nonpayable",
    "type": "function"
  },
  {
    "inputs": [
      {
        "internalType": "bytes",
        "name": "",
        "type": "bytes"
      }
    ],
    "name": "checkUpkeep",
    "outputs": [
      {
        "internalType": "bool",
        "name": "upkeepNeeded",
        "type": "bool"
      },
      {
        "internalType": "bytes",
        "name": "performData",
        "type": "bytes"
      }
    ],
    "stateMutability": "view",
    "type": "function"
  },
  {
    "inputs": [
      {
        "internalType": "uint256",
        "name": "",
        "type": "uint256"
      }
    ],
    "name": "contracts",
    "outputs": [
      {
        "internalType": "address",
        "name": "",
        "type": "address"
      }
    ],
    "stateMutability": "view",
    "type": "function"
  },
  {
    "inputs": [],
    "name": "monthCount",
    "outputs": [
      {
        "internalType": "uint128",
        "name": "",
        "type": "uint128"
      }
    ],
    "stateMutability": "view",
    "type": "function"
  },
  {
    "inputs": [],
    "name": "owner",
    "outputs": [
      {
        "internalType": "address",
        "name": "",
        "type": "address"
      }
    ],
    "stateMutability": "view",
    "type": "function"
  },
  {
    "inputs": [],
    "name": "payroundStartTime",
    "outputs": [
      {
        "internalType": "uint256",
        "name": "",
        "type": "uint256"
      }
    ],
    "stateMutability": "view",
    "type": "function"
  },
  {
    "inputs": [
      {
        "internalType": "bytes",
        "name": "performData",
        "type": "bytes"
      }
    ],
    "name": "performUpkeep",
    "outputs": [],
    "stateMutability": "nonpayable",
    "type": "function"
  },
  {
    "inputs": [
      {
        "internalType": "address",
        "name": "",
        "type": "address"
      }
    ],
    "name": "presentCharities",
    "outputs": [
      {
        "internalType": "bytes8",
        "name": "name",
        "type": "bytes8"
      },
      {
        "internalType": "bytes32",
        "name": "link",
        "type": "bytes32"
      }
    ],
    "stateMutability": "view",
    "type": "function"
  },
  {
    "inputs": [],
    "name": "renounceOwnership",
    "outputs": [],
    "stateMutability": "nonpayable",
    "type": "function"
  },
  {
    "inputs": [
      {
        "internalType": "uint128",
        "name": "",
        "type": "uint128"
      },
      {
        "internalType": "bytes8",
        "name": "",
        "type": "bytes8"
      }
    ],
    "name": "roundCharityVotes",
    "outputs": [
      {
        "internalType": "uint128",
        "name": "",
        "type": "uint128"
      }
    ],
    "stateMutability": "view",
    "type": "function"
  },
  {
    "inputs": [
      {
        "internalType": "uint128",
        "name": "",
        "type": "uint128"
      }
    ],
    "name": "roundVoteResults",
    "outputs": [
      {
        "internalType": "address",
        "name": "",
        "type": "address"
      }
    ],
    "stateMutability": "view",
    "type": "function"
  },
  {
    "inputs": [],
    "name": "setwinningCharity",
    "outputs": [],
    "stateMutability": "nonpayable",
    "type": "function"
  },
  {
    "inputs": [],
    "name": "totalInIBA",
    "outputs": [
      {
        "internalType": "uint256",
        "name": "",
        "type": "uint256"
      }
    ],
    "stateMutability": "view",
    "type": "function"
  },
  {
    "inputs": [
      {
        "internalType": "address",
        "name": "newOwner",
        "type": "address"
      }
    ],
    "name": "transferOwnership",
    "outputs": [],
    "stateMutability": "nonpayable",
    "type": "function"
  },
  {
    "inputs": [
      {
        "internalType": "bytes8",
        "name": "charity",
        "type": "bytes8"
      }
    ],
    "name": "voteForCharity",
    "outputs": [],
    "stateMutability": "nonpayable",
    "type": "function"
  },
  {
    "inputs": [
      {
        "internalType": "uint256",
        "name": "amount_",
        "type": "uint256"
      }
    ],
    "name": "withdrawRoundFunds",
    "outputs": [],
    "stateMutability": "nonpayable",
    "type": "function"
  }
]
